{
	"_id": "59e4cf5286f7741778269d8a",
	"_name": "patron_762x39_T45M",
	"_parent": "5485a8684bdc2da71d8b4567",
	"_type": "Item",
	"_props": {
		"Name": "patron_762x39_T45M",
		"ShortName": "patron_762x39_T45M",
		"Description": "patron_762x39_T45M",
		"Weight": 0.01,
		"BackgroundColor": "yellow",
		"Width": 1,
		"Height": 1,
		"StackMaxSize": 60,
		"Rarity": "Not_exist",
		"SpawnChance": 50,
		"CreditsPrice": 58,
		"ItemSound": "ammo_singleround",
		"Prefab": {
			"path": "assets/content/items/ammo/patrons/patron_762x39.bundle",
			"rcid": ""
		},
		"UsePrefab": {
			"path": "",
			"rcid": ""
		},
		"StackObjectsCount": 1,
		"NotShownInSlot": false,
		"ExaminedByDefault": true,
		"ExamineTime": 1,
		"IsUndiscardable": false,
		"IsUnsaleable": false,
		"IsUnbuyable": false,
		"IsUngivable": false,
		"IsLockedafterEquip": false,
		"QuestItem": false,
		"LootExperience": 0,
		"ExamineExperience": 10,
		"HideEntrails": false,
		"RepairCost": 0,
		"RepairSpeed": 0,
		"ExtraSizeLeft": 0,
		"ExtraSizeRight": 0,
		"ExtraSizeUp": 0,
		"ExtraSizeDown": 0,
		"ExtraSizeForceAdd": false,
		"MergesWithChildren": false,
		"BannedFromRagfair": false,
		"ConflictingItems": [],
		"FixedPrice": false,
		"Unlootable": false,
		"UnlootableFromSlot": "FirstPrimaryWeapon",
		"UnlootableFromSide": [],
		"ChangePriceCoef": 1,
		"AllowSpawnOnLocations": [],
		"SendToClient": false,
		"StackMinRandom": 3,
		"StackMaxRandom": 15,
		"ammoType": "bullet",
		"Damage": 58,
		"ammoAccr": 0,
		"ammoRec": 0,
		"ammoDist": 0,
		"buckshotBullets": 0,
		"PenetrationPower": 26,
		"PenetrationPowerDiviation": 0.27,
		"ammoHear": 0,
		"ammoSfx": "standart",
		"MisfireChance": 0.01,
		"MinFragmentsCount": 2,
		"MaxFragmentsCount": 4,
		"ammoShiftChance": 0,
		"casingName": "7.62x39 мм T45M",
		"casingEjectPower": 0,
		"casingMass": 16.5,
		"casingSounds": "rifle556",
		"ProjectileCount": 1,
		"InitialSpeed": 720,
		"PenetrationChance": 0.63,
		"RicochetChance": 0.35,
		"FragmentationChance": 0.12,
		"BallisticCoeficient": 1,
		"Deterioration": 1,
		"SpeedRetardation": 0.000025,
		"Tracer": true,
		"TracerColor": "red",
		"TracerDistance": 0.5,
		"ArmorDamage": 48,
		"Caliber": "Caliber762x39",
		"StaminaBurnPerDamage": 0.5
	},
	"_proto": "56dff338d2720bbd668b4569"
}