{
	"_id": "5d1f566d86f7744bcd13459a",
	"_name": "bear_upper_blacklynx",
	"_parent": "5cc0868e14c02e000c6bea68",
	"_type": "Item",
	"_props": {
		"Name": "DeafaultBearBody",
		"ShortName": "DeafaultBearBody",
		"Description": "DeafaultBearBody",
		"Side": [
			"Bear"
		],
		"BodyPart": "Body",
		"Prefab": {
			"path": "assets/content/characters/character/prefabs/top_bear_blacklynx.bundle",
			"rcid": ""
		},
		"WatchPrefab": {
			"path": "",
			"rcid": ""
		},
		"IntegratedArmorVest": false,
		"WatchPosition": {
			"x": 0,
			"y": 0,
			"z": 0
		},
		"WatchRotation": {
			"x": 0,
			"y": 0,
			"z": 0
		}
	},
	"_proto": "5cc0858d14c02e000c6bea66"
}