{
	"items": [
		{
			"_id": "5dcc042f06b06a0f045f5996",
			"_tpl": "55d7217a4bdc2d86028b456d"
		},
		{
			"_id": "5dcc042f06b06a0f045f59bc",
			"_tpl": "5ab8e9fcd8ce870019439434",
			"parentId": "5dcc042f06b06a0f045f5996",
			"slotId": "FirstPrimaryWeapon",
			"upd": {
				"Foldable": {
					"Folded": false
				},
				"Togglable": {
					"On": true
				}
			}
		},
		{
			"_id": "5dcc042f06b06a0f045f59bd",
			"_tpl": "59e649f986f77411d949b246",
			"parentId": "5dcc042f06b06a0f045f59bc",
			"slotId": "mod_gas_block"
		},
		{
			"_id": "5dcc042f06b06a0f045f59be",
			"_tpl": "5a9d56c8a2750c0032157146",
			"parentId": "5dcc042f06b06a0f045f59bd",
			"slotId": "mod_handguard"
		},
		{
			"_id": "5dcc042f06b06a0f045f59bf",
			"_tpl": "59e0be5d86f7742d48765bd2",
			"parentId": "5dcc042f06b06a0f045f59be",
			"slotId": "mod_mount_001"
		},
		{
			"_id": "5dcc042f06b06a0f045f59c0",
			"_tpl": "5a7b483fe899ef0016170d15",
			"parentId": "5dcc042f06b06a0f045f59bf",
			"slotId": "mod_tactical"
		},
		{
			"_id": "5dcc042f06b06a0f045f59c1",
			"_tpl": "5943eeeb86f77412d6384f6b",
			"parentId": "5dcc042f06b06a0f045f59bc",
			"slotId": "mod_muzzle"
		},
		{
			"_id": "5dcc042f06b06a0f045f59c2",
			"_tpl": "5998517986f7746017232f7e",
			"parentId": "5dcc042f06b06a0f045f59bc",
			"slotId": "mod_pistol_grip"
		},
		{
			"_id": "5dcc042f06b06a0f045f59c6",
			"_tpl": "5ab626e4d8ce87272e4c6e43",
			"parentId": "5dcc042f06b06a0f045f59bc",
			"slotId": "mod_stock",
			"upd": {
				"Foldable": {
					"Folded": false
				}
			}
		},
		{
			"_id": "5dcc042f06b06a0f045f59c9",
			"_tpl": "5d2c76ed48f03532f2136169",
			"parentId": "5dcc042f06b06a0f045f59bc",
			"slotId": "mod_reciever"
		},
		{
			"_id": "5dcc042f06b06a0f045f59ca",
			"_tpl": "584984812459776a704a82a6",
			"parentId": "5dcc042f06b06a0f045f59c9",
			"slotId": "mod_scope"
		},
		{
			"_id": "5dcc042f06b06a0f045f59cb",
			"_tpl": "55d480c04bdc2d1d4e8b456a",
			"parentId": "5dcc042f06b06a0f045f59bc",
			"slotId": "mod_magazine"
		},
		{
			"_id": "5dcc042f06b06a0f045f59cc",
			"_tpl": "56dff061d2720bb5668b4567",
			"parentId": "5dcc042f06b06a0f045f59cb",
			"slotId": "cartridges",
			"upd": {
				"StackObjectsCount": 30
			}
		},
		{
			"_id": "5dcc042f06b06a0f045f59cd",
			"_tpl": "557ffd194bdc2d28148b457f",
			"parentId": "5dcc042f06b06a0f045f5996",
			"slotId": "Pockets"
		},
		{
			"_id": "5dcc042f06b06a0f045f59e1",
			"_tpl": "5710c24ad2720bc3458b45a3",
			"parentId": "5dcc042f06b06a0f045f59cd",
			"slotId": "pocket1",
			"location": {
				"x": 0,
				"y": 0,
				"r": 0
			}
		},
		{
			"_id": "5dcc042f06b06a0f045f59e2",
			"_tpl": "5710c24ad2720bc3458b45a3",
			"parentId": "5dcc042f06b06a0f045f59cd",
			"slotId": "pocket2",
			"location": {
				"x": 0,
				"y": 0,
				"r": 0
			}
		},
		{
			"_id": "5dcc042f06b06a0f045f59ce",
			"_tpl": "544a5caa4bdc2d1a388b4568",
			"parentId": "5dcc042f06b06a0f045f5996",
			"slotId": "TacticalVest"
		},
		{
			"_id": "5dcc042f06b06a0f045f59db",
			"_tpl": "55d480c04bdc2d1d4e8b456a",
			"parentId": "5dcc042f06b06a0f045f59ce",
			"slotId": "1",
			"location": {
				"x": 0,
				"y": 0,
				"r": 0
			}
		},
		{
			"_id": "5dcc042f06b06a0f045f59dc",
			"_tpl": "56dff061d2720bb5668b4567",
			"parentId": "5dcc042f06b06a0f045f59db",
			"slotId": "cartridges",
			"upd": {
				"StackObjectsCount": 30
			}
		},
		{
			"_id": "5dcc042f06b06a0f045f59dd",
			"_tpl": "55d480c04bdc2d1d4e8b456a",
			"parentId": "5dcc042f06b06a0f045f59ce",
			"slotId": "2",
			"location": {
				"x": 0,
				"y": 0,
				"r": 0
			}
		},
		{
			"_id": "5dcc042f06b06a0f045f59de",
			"_tpl": "56dff061d2720bb5668b4567",
			"parentId": "5dcc042f06b06a0f045f59dd",
			"slotId": "cartridges",
			"upd": {
				"StackObjectsCount": 30
			}
		},
		{
			"_id": "5dcc042f06b06a0f045f59cf",
			"_tpl": "5a7c4850e899ef00150be885",
			"parentId": "5dcc042f06b06a0f045f5996",
			"slotId": "Headwear",
			"upd": {
				"Repairable": {
					"Durability": 25
				}
			}
		},
		{
			"_id": "5dcc042f06b06a0f045f59d0",
			"_tpl": "5bc9c1e2d4351e00367fbcf0",
			"parentId": "5dcc042f06b06a0f045f5996",
			"slotId": "Scabbard"
		},
		{
			"_id": "5dcc042f06b06a0f045f59d1",
			"_tpl": "5857a8bc2459772bad15db29",
			"parentId": "5dcc042f06b06a0f045f5996",
			"slotId": "SecuredContainer"
		},
		{
			"_id": "5dcc042f06b06a0f045f59d2",
			"_tpl": "56dff061d2720bb5668b4567",
			"parentId": "5dcc042f06b06a0f045f59d1",
			"slotId": "main",
			"location": {
				"x": 0,
				"y": 0,
				"r": 0
			},
			"upd": {
				"StackObjectsCount": 60
			}
		},
		{
			"_id": "5dcc042f06b06a0f045f59d3",
			"_tpl": "56dff061d2720bb5668b4567",
			"parentId": "5dcc042f06b06a0f045f59d1",
			"slotId": "main",
			"location": {
				"x": 1,
				"y": 0,
				"r": 0
			},
			"upd": {
				"StackObjectsCount": 60
			}
		},
		{
			"_id": "5dcc042f06b06a0f045f59d4",
			"_tpl": "56dff061d2720bb5668b4567",
			"parentId": "5dcc042f06b06a0f045f59d1",
			"slotId": "main",
			"location": {
				"x": 2,
				"y": 0,
				"r": 0
			},
			"upd": {
				"StackObjectsCount": 60
			}
		},
		{
			"_id": "5dcc042f06b06a0f045f59d5",
			"_tpl": "56dff061d2720bb5668b4567",
			"parentId": "5dcc042f06b06a0f045f59d1",
			"slotId": "main",
			"location": {
				"x": 0,
				"y": 1,
				"r": 0
			},
			"upd": {
				"StackObjectsCount": 60
			}
		},
		{
			"_id": "5dcc042f06b06a0f045f59d6",
			"_tpl": "56dff061d2720bb5668b4567",
			"parentId": "5dcc042f06b06a0f045f59d1",
			"slotId": "main",
			"location": {
				"x": 1,
				"y": 1,
				"r": 0
			},
			"upd": {
				"StackObjectsCount": 60
			}
		},
		{
			"_id": "5dcc042f06b06a0f045f59d7",
			"_tpl": "56dff061d2720bb5668b4567",
			"parentId": "5dcc042f06b06a0f045f59d1",
			"slotId": "main",
			"location": {
				"x": 2,
				"y": 1,
				"r": 0
			},
			"upd": {
				"StackObjectsCount": 60
			}
		},
		{
			"_id": "5dcc042f06b06a0f045f59d8",
			"_tpl": "56dff061d2720bb5668b4567",
			"parentId": "5dcc042f06b06a0f045f59d1",
			"slotId": "main",
			"location": {
				"x": 0,
				"y": 2,
				"r": 0
			},
			"upd": {
				"StackObjectsCount": 60
			}
		},
		{
			"_id": "5dcc042f06b06a0f045f59d9",
			"_tpl": "56dff061d2720bb5668b4567",
			"parentId": "5dcc042f06b06a0f045f59d1",
			"slotId": "main",
			"location": {
				"x": 1,
				"y": 2,
				"r": 0
			},
			"upd": {
				"StackObjectsCount": 60
			}
		},
		{
			"_id": "5dcc042f06b06a0f045f59da",
			"_tpl": "56dff061d2720bb5668b4567",
			"parentId": "5dcc042f06b06a0f045f59d1",
			"slotId": "main",
			"location": {
				"x": 2,
				"y": 2,
				"r": 0
			},
			"upd": {
				"StackObjectsCount": 60
			}
		},
		{
			"_id": "5dcc042f06b06a0f045f5995",
			"_tpl": "566abbc34bdc2d92178b4576"
		},
		{
			"_id": "5dcc042f06b06a0f045f5998",
			"_tpl": "5963866b86f7747bfa1c4462"
		},
		{
			"_id": "5dcc042f06b06a0f045f5997",
			"_tpl": "5963866286f7747bf429b572"
		}
	],
	"equipment": "5dcc042f06b06a0f045f5996",
	"stash": "5dcc042f06b06a0f045f5995",
	"questRaidItems": "5dcc042f06b06a0f045f5997",
	"questStashItems": "5dcc042f06b06a0f045f5998",
	"fastPanel": {}
}